{
  "name": "Npp",
  "plural": "npp",
  "base": "User",
  "idInjection": true,
  "options": {
    "validateUpsert": true
  },
  "properties": {
    "dtId": {
      "type": "number"
    }
  },
  "validations": [],
  "relations": {},
  "acls": [
    {
      "accessType": "*",
      "principalType": "ROLE",
      "principalId": "admin",
      "permission": "ALLOW"
    },
    {
      "accessType": "READ",
      "principalType": "ROLE",
      "principalId": "npp",
      "permission": "ALLOW"
    },
    {
      "accessType": "*",
      "principalType": "ROLE",
      "principalId": "$everyone",
      "permission": "DENY"
    }
  ],
  "methods": {}
}
